README.md
setup.py
metafinder/__init__.py
metafinder/cli.py
metafinder/core.py
metafinder/extractor.py
metafinder.egg-info/PKG-INFO
metafinder.egg-info/SOURCES.txt
metafinder.egg-info/dependency_links.txt
metafinder.egg-info/entry_points.txt
metafinder.egg-info/requires.txt
metafinder.egg-info/top_level.txt
metafinder/utils/__init__.py
metafinder/utils/agent.py
metafinder/utils/banner.py
metafinder/utils/color_print.py
metafinder/utils/exception.py
metafinder/utils/library.py
metafinder/utils/result.py
metafinder/utils/var_data.py
metafinder/utils/file/__init__.py
metafinder/utils/file/download.py
metafinder/utils/file/metadata.py
metafinder/utils/file/parser.py
metafinder/utils/finder/__init__.py
metafinder/utils/finder/baidu.py
metafinder/utils/finder/bing.py
metafinder/utils/finder/google.py