Metadata-Version: 2.1
Name: metafinder
Version: 0.3.2b0
Summary: MetaFinder - Metadata search through Search Engines
Home-page: https://github.com/Josue87/MetaFinder
Author: Josue Encinar (@JosueEncinar)
License: GNU GPLv3+
Platform: UNKNOWN
